.gitignore
LICENSE
README.md
setup.cfg
setup.py
doc/example.png
src/CobolSharp/__init__.py
src/CobolSharp/analyze.py
src/CobolSharp/command.py
src/CobolSharp/format.py
src/CobolSharp/graph.py
src/CobolSharp/koopa.py
src/CobolSharp/output.py
src/CobolSharp/structure.py
src/CobolSharp/syntax.py
src/CobolSharp/data/koopa-r356.jar
src/CobolSharp/templates/main.html
src/CobolSharp/templates/source.css
src/CobolSharp/templates/ui.js
src/cobolsharp.egg-info/PKG-INFO
src/cobolsharp.egg-info/SOURCES.txt
src/cobolsharp.egg-info/dependency_links.txt
src/cobolsharp.egg-info/eager_resources.txt
src/cobolsharp.egg-info/entry_points.txt
src/cobolsharp.egg-info/not-zip-safe
src/cobolsharp.egg-info/requires.txt
src/cobolsharp.egg-info/top_level.txt
src/tests/__init__.py
src/tests/analyze_basic_test.py
src/tests/analyze_branch_test.py
src/tests/analyze_loop_test.py
src/tests/conftest.py
src/tools/cobolsharp
test/crossedbranches.cbl
test/loops.cbl
test/testsyntax.cbl